foliant/preprocessors/swaggerdoc/__init__.py
foliant/preprocessors/swaggerdoc/swaggerdoc.py
foliant/preprocessors/swaggerdoc/template/swagger.j2
foliantcontrib.swaggerdoc-1.2.6.dist-info/LICENSE
foliantcontrib.swaggerdoc-1.2.6.dist-info/METADATA
foliantcontrib.swaggerdoc-1.2.6.dist-info/WHEEL
foliantcontrib.swaggerdoc-1.2.6.dist-info/top_level.txt
foliantcontrib.swaggerdoc-1.2.6.dist-info/RECORD
