Metadata-Version: 2.2
Name: foliantcontrib.swaggerdoc
Version: 1.2.6
Summary: Documentation generator for Swagger API
Author: Daniil Minukhin
Author-email: ddddsa@gmail.com
License: MIT
Platform: any
Classifier: Development Status :: 5 - Production/Stable
Classifier: Environment :: Console
Classifier: Intended Audience :: Developers
Classifier: License :: OSI Approved :: MIT License
Classifier: Operating System :: OS Independent
Classifier: Programming Language :: Python
Classifier: Topic :: Documentation
Classifier: Topic :: Utilities
License-File: LICENSE
Requires-Dist: foliant>=1.0.5
Requires-Dist: jinja2
Requires-Dist: ruamel.yaml==0.17.40
Requires-Dist: foliantcontrib.utils>=1.0.2
Dynamic: author
Dynamic: author-email
Dynamic: classifier
Dynamic: description
Dynamic: description-content-type
Dynamic: license
Dynamic: platform
Dynamic: requires-dist
Dynamic: summary
